README.rst
setup.py
astra/__init__.py
astra/fields.py
astra/models.py
astra/validators.py
redis_astra.egg-info/PKG-INFO
redis_astra.egg-info/SOURCES.txt
redis_astra.egg-info/dependency_links.txt
redis_astra.egg-info/requires.txt
redis_astra.egg-info/top_level.txt