Metadata-Version: 2.1
Name: redis-astra
Version: 2.0.0
Summary: ORM for Redis
Home-page: https://github.com/pilat/redis-astra
Author: Vladimir K Urushev
Author-email: urushev@yandex.ru
Maintainer: Vladimir K Urushev
Maintainer-email: urushev@yandex.ru
License: MIT
Download-URL: https://github.com/pilat/redis-astra/tarball/2.0.0
Keywords: Redis,ORM
Platform: UNKNOWN
Classifier: Development Status :: 3 - Alpha
Classifier: Intended Audience :: Developers
Classifier: License :: OSI Approved :: MIT License
Classifier: Programming Language :: Python
Classifier: Programming Language :: Python :: 2.6
Classifier: Programming Language :: Python :: 2.7
Classifier: Programming Language :: Python :: 3
Classifier: Programming Language :: Python :: 3.3
Classifier: Programming Language :: Python :: 3.4
Classifier: Programming Language :: Python :: 3.5
Provides-Extra: test
Provides-Extra: dev
